{
  "id" : "city.fk_city_country",
  "name" : "fk_city_country",
  "method" : "BTREE",
  "unique" : false,
  "type" : {
    "table" : {
      "ref" : {
        "id" : "city",
        "tableName" : "city",
        "containerName" : "prod-med19"
      },
      "columns" : [ {
        "ref" : {
          "container" : "prod-med19",
          "tableName" : "city",
          "columnName" : "country_id"
        },
        "position" : 1
      } ]
    }
  },
  "properties" : {
    "keyBlockSize" : 0,
    "comment" : ""
  }
}